README.md
setup.cfg
setup.py
bin/databrickstools
src/databrickstools/__init__.py
src/databrickstools/__main__.py
src/databrickstools/core.py
src/databrickstools/databricks.py
src/databrickstools/markdown.py
src/databrickstools/settings.py
src/databrickstools/utils.py
src/databrickstools.egg-info/PKG-INFO
src/databrickstools.egg-info/SOURCES.txt
src/databrickstools.egg-info/dependency_links.txt
src/databrickstools.egg-info/entry_points.txt
src/databrickstools.egg-info/requires.txt
src/databrickstools.egg-info/top_level.txt