Metadata-Version: 2.1
Name: databrickstools
Version: 0.3.1
Summary: A simple commandline application to manage databricks resources.
Home-page: https://github.com/rhdzmota/databrickstools-cli
Author: Rodrigo Hernández Mota
Author-email: contact@rhdzmota.com
License: LICENSE.md
Platform: UNKNOWN
Classifier: Programming Language :: Python :: 3.6
Classifier: Programming Language :: Python :: 3.7
Classifier: Programming Language :: Python :: 3.8
Requires-Python: >=3.5, <4
